[
  {
    "name": "Nomad (Vanilla)",
    "min_wear": 0,
    "max_wear": 1,
    "trade_up": false,
    "weapon_id": 521,
    "gen_id": 0,
    "collection": "Nomad",
    "rarity": "Covert"
  },
  {
    "name": "Nomad | Gamma Doppler (Phase 1)",
    "min_wear": 0,
    "max_wear": 0.08,
    "trade_up": false,
    "weapon_id": 521,
    "gen_id": 569,
    "collection": "Nomad",
    "rarity": "Covert"
  },
  {
    "name": "Nomad | Gamma Doppler (Phase 2)",
    "min_wear": 0,
    "max_wear": 0.08,
    "trade_up": false,
    "weapon_id": 521,
    "gen_id": 570,
    "collection": "Nomad",
    "rarity": "Covert"
  },
  {
    "name": "Nomad | Gamma Doppler (Phase 3)",
    "min_wear": 0,
    "max_wear": 0.08,
    "trade_up": false,
    "weapon_id": 521,
    "gen_id": 571,
    "collection": "Nomad",
    "rarity": "Covert"
  },
  {
    "name": "Nomad | Gamma Doppler (Phase 4)",
    "min_wear": 0,
    "max_wear": 0.08,
    "trade_up": false,
    "weapon_id": 521,
    "gen_id": 572,
    "collection": "Nomad",
    "rarity": "Covert"
  },
  {
    "name": "Nomad | Gamma Doppler (Emerald)",
    "min_wear": 0,
    "max_wear": 0.08,
    "trade_up": false,
    "weapon_id": 521,
    "gen_id": 568,
    "collection": "Nomad",
    "rarity": "Covert"
  },
  {
    "name": "Nomad | Lore",
    "min_wear": 0,
    "max_wear": 1,
    "trade_up": false,
    "weapon_id": 521,
    "gen_id": 558,
    "collection": "Nomad",
    "rarity": "Covert"
  },
  {
    "name": "Nomad | Autotronic",
    "min_wear": 0,
    "max_wear": 0.85,
    "trade_up": false,
    "weapon_id": 521,
    "gen_id": 573,
    "collection": "Nomad",
    "rarity": "Covert"
  },
  {
    "name": "Nomad | Black Laminate",
    "min_wear": 0,
    "max_wear": 1,
    "trade_up": false,
    "weapon_id": 521,
    "gen_id": 563,
    "collection": "Nomad",
    "rarity": "Covert"
  },
  {
    "name": "Nomad | Freehand",
    "min_wear": 0,
    "max_wear": 0.48,
    "trade_up": false,
    "weapon_id": 521,
    "gen_id": 580,
    "collection": "Nomad",
    "rarity": "Covert"
  },
  {
    "name": "Nomad | Bright Water",
    "min_wear": 0,
    "max_wear": 0.5,
    "trade_up": false,
    "weapon_id": 521,
    "gen_id": 578,
    "collection": "Nomad",
    "rarity": "Covert"
  },
  {
    "name": "Nomad | Marble Fade",
    "min_wear": 0,
    "max_wear": 0.08,
    "trade_up": false,
    "weapon_id": 521,
    "gen_id": 413,
    "collection": "Nomad",
    "rarity": "Covert"
  },
  {
    "name": "Nomad | Tiger Tooth",
    "min_wear": 0,
    "max_wear": 0.08,
    "trade_up": false,
    "weapon_id": 521,
    "gen_id": 409,
    "collection": "Nomad",
    "rarity": "Covert"
  },
  {
    "name": "Nomad | Doppler (Phase 1)",
    "min_wear": 0,
    "max_wear": 0.08,
    "trade_up": false,
    "weapon_id": 521,
    "gen_id": 418,
    "collection": "Nomad",
    "rarity": "Covert"
  },
  {
    "name": "Nomad | Doppler (Phase 2)",
    "min_wear": 0,
    "max_wear": 0.08,
    "trade_up": false,
    "weapon_id": 521,
    "gen_id": 419,
    "collection": "Nomad",
    "rarity": "Covert"
  },
  {
    "name": "Nomad | Doppler (Phase 3)",
    "min_wear": 0,
    "max_wear": 0.08,
    "trade_up": false,
    "weapon_id": 521,
    "gen_id": 420,
    "collection": "Nomad",
    "rarity": "Covert"
  },
  {
    "name": "Nomad | Doppler (Phase 4)",
    "min_wear": 0,
    "max_wear": 0.08,
    "trade_up": false,
    "weapon_id": 521,
    "gen_id": 421,
    "collection": "Nomad",
    "rarity": "Covert"
  },
  {
    "name": "Nomad | Doppler (Ruby)",
    "min_wear": 0,
    "max_wear": 0.08,
    "trade_up": false,
    "weapon_id": 521,
    "gen_id": 415,
    "collection": "Nomad",
    "rarity": "Covert"
  },
  {
    "name": "Nomad | Doppler (Saphire)",
    "min_wear": 0,
    "max_wear": 0.08,
    "trade_up": false,
    "weapon_id": 521,
    "gen_id": 416,
    "collection": "Nomad",
    "rarity": "Covert"
  },
  {
    "name": "Nomad | Doppler (Black Pearl)",
    "min_wear": 0,
    "max_wear": 0.08,
    "trade_up": false,
    "weapon_id": 521,
    "gen_id": 417,
    "collection": "Nomad",
    "rarity": "Covert"
  },
  {
    "name": "Nomad | Damascus Steel",
    "min_wear": 0,
    "max_wear": 0.5,
    "trade_up": false,
    "weapon_id": 521,
    "gen_id": 410,
    "collection": "Nomad",
    "rarity": "Covert"
  },
  {
    "name": "Nomad | Ultraviolet",
    "min_wear": 0.06,
    "max_wear": 0.8,
    "trade_up": false,
    "weapon_id": 521,
    "gen_id": 98,
    "collection": "Nomad",
    "rarity": "Covert"
  },
  {
    "name": "Nomad | Rust Coat",
    "min_wear": 0.4,
    "max_wear": 1,
    "trade_up": false,
    "weapon_id": 521,
    "gen_id": 414,
    "collection": "Nomad",
    "rarity": "Covert"
  },
  {
    "name": "Nomad | Fade",
    "min_wear": 0,
    "max_wear": 0.08,
    "trade_up": false,
    "weapon_id": 521,
    "gen_id": 38,
    "collection": "Nomad",
    "rarity": "Covert"
  },
  {
    "name": "Nomad | Slaughter",
    "min_wear": 0.01,
    "max_wear": 0.26,
    "trade_up": false,
    "weapon_id": 521,
    "gen_id": 59,
    "collection": "Nomad",
    "rarity": "Covert"
  },
  {
    "name": "Nomad | Case Hardened",
    "min_wear": 0,
    "max_wear": 1,
    "trade_up": false,
    "weapon_id": 521,
    "gen_id": 44,
    "collection": "Nomad",
    "rarity": "Covert"
  },
  {
    "name": "Nomad | Blue Steel",
    "min_wear": 0,
    "max_wear": 1,
    "trade_up": false,
    "weapon_id": 521,
    "gen_id": 42,
    "collection": "Nomad",
    "rarity": "Covert"
  },
  {
    "name": "Nomad | Stained",
    "min_wear": 0,
    "max_wear": 1,
    "trade_up": false,
    "weapon_id": 521,
    "gen_id": 43,
    "collection": "Nomad",
    "rarity": "Covert"
  },
  {
    "name": "Nomad | Crimson Web",
    "min_wear": 0.06,
    "max_wear": 0.8,
    "trade_up": false,
    "weapon_id": 521,
    "gen_id": 12,
    "collection": "Nomad",
    "rarity": "Covert"
  },
  {
    "name": "Nomad | Boreal Forest",
    "min_wear": 0.06,
    "max_wear": 0.8,
    "trade_up": false,
    "weapon_id": 521,
    "gen_id": 77,
    "collection": "Nomad",
    "rarity": "Covert"
  },
  {
    "name": "Nomad | Night Stripe",
    "min_wear": 0.06,
    "max_wear": 0.8,
    "trade_up": false,
    "weapon_id": 521,
    "gen_id": 735,
    "collection": "Nomad",
    "rarity": "Covert"
  },
  {
    "name": "Nomad | Safari Mesh",
    "min_wear": 0.06,
    "max_wear": 0.8,
    "trade_up": false,
    "weapon_id": 521,
    "gen_id": 72,
    "collection": "Nomad",
    "rarity": "Covert"
  },
  {
    "name": "Nomad | Urban Masked",
    "min_wear": 0.06,
    "max_wear": 0.8,
    "trade_up": false,
    "weapon_id": 521,
    "gen_id": 143,
    "collection": "Nomad",
    "rarity": "Covert"
  },
  {
    "name": "Nomad | Forest DDPAT",
    "min_wear": 0.06,
    "max_wear": 0.8,
    "trade_up": false,
    "weapon_id": 521,
    "gen_id": 5,
    "collection": "Nomad",
    "rarity": "Covert"
  },
  {
    "name": "Nomad | Scorched",
    "min_wear": 0.06,
    "max_wear": 0.8,
    "trade_up": false,
    "weapon_id": 521,
    "gen_id": 5,
    "collection": "Nomad",
    "rarity": "Covert"
  }
]