[
  {
    "name": "MAG-7 | Bulldozer",
    "min_wear": 0.06,
    "max_wear": 0.8,
    "trade_up": false,
    "weapon_id": 27,
    "gen_id": 39,
    "collection": "The Mirage Collection",
    "rarity": "Restricted",
    "Image": "/assets/img/items/weapons/themiragecollection/mag-7-bulldozer.png",
    "IsKnife": false,
    "StickerSlotsAmount": 4,
    "RarityId": 4
  },
  {
    "name": "MP9 | Hot Rod",
    "min_wear": 0,
    "max_wear": 0.08,
    "trade_up": true,
    "weapon_id": 34,
    "gen_id": 33,
    "collection": "The Mirage Collection",
    "rarity": "Milspec",
    "Image": "/assets/img/items/weapons/themiragecollection/mp9-hotrod.png",
    "IsKnife": false,
    "StickerSlotsAmount": 4,
    "RarityId": 3
  },
  {
    "name": "UMP-45 | Blaze",
    "min_wear": 0,
    "max_wear": 0.08,
    "trade_up": true,
    "weapon_id": 24,
    "gen_id": 37,
    "collection": "The Mirage Collection",
    "rarity": "Milspec",
    "Image": "/assets/img/items/weapons/themiragecollection/ump-45-blaze.png",
    "IsKnife": false,
    "StickerSlotsAmount": 4,
    "RarityId": 3
  },
  {
    "name": "MAC-10 | Amber Fade",
    "min_wear": 0,
    "max_wear": 0.4,
    "trade_up": true,
    "weapon_id": 17,
    "gen_id": 246,
    "collection": "The Mirage Collection",
    "rarity": "Milspec",
    "Image": "/assets/img/items/weapons/themiragecollection/mac-10-amberfade.png",
    "IsKnife": false,
    "StickerSlotsAmount": 4,
    "RarityId": 3
  },
  {
    "name": "Glock-18 | Groundwater",
    "min_wear": 0.06,
    "max_wear": 0.8,
    "trade_up": true,
    "weapon_id": 4,
    "gen_id": 2,
    "collection": "The Mirage Collection",
    "rarity": "Industrial",
    "Image": "/assets/img/items/weapons/themiragecollection/glock-18-groundwater.png",
    "IsKnife": false,
    "StickerSlotsAmount": 4,
    "RarityId": 2
  },
  {
    "name": "SSG 08 | Tropical Storm",
    "min_wear": 0.06,
    "max_wear": 0.8,
    "trade_up": true,
    "weapon_id": 40,
    "gen_id": 233,
    "collection": "The Mirage Collection",
    "rarity": "Industrial",
    "Image": "/assets/img/items/weapons/themiragecollection/ssg08-tropicalstorm.png",
    "IsKnife": false,
    "StickerSlotsAmount": 4,
    "RarityId": 2
  },
  {
    "name": "MP7 | Orange Peel",
    "min_wear": 0.06,
    "max_wear": 0.8,
    "trade_up": true,
    "weapon_id": 33,
    "gen_id": 141,
    "collection": "The Mirage Collection",
    "rarity": "Industrial",
    "Image": "/assets/img/items/weapons/themiragecollection/mp7-orangepeel.png",
    "IsKnife": false,
    "StickerSlotsAmount": 4,
    "RarityId": 2
  },
  {
    "name": "Negev | CaliCamo",
    "min_wear": 0,
    "max_wear": 0.6,
    "trade_up": true,
    "weapon_id": 28,
    "gen_id": 240,
    "collection": "The Mirage Collection",
    "rarity": "Industrial",
    "Image": "/assets/img/items/weapons/themiragecollection/negev-calicamo.png",
    "IsKnife": false,
    "StickerSlotsAmount": 4,
    "RarityId": 2
  },
  {
    "name": "SG 553 | Gator Mesh",
    "min_wear": 0,
    "max_wear": 0.6,
    "trade_up": true,
    "weapon_id": 39,
    "gen_id": 243,
    "collection": "The Mirage Collection",
    "rarity": "Industrial",
    "Image": "/assets/img/items/weapons/themiragecollection/sg553-gatormesh.png",
    "IsKnife": false,
    "StickerSlotsAmount": 4,
    "RarityId": 2
  },
  {
    "name": "Five-SeveN | Contractor",
    "min_wear": 0.06,
    "max_wear": 0.8,
    "trade_up": true,
    "weapon_id": 3,
    "gen_id": 46,
    "collection": "The Mirage Collection",
    "rarity": "Consumer",
    "Image": "/assets/img/items/weapons/themiragecollection/five-seven-contractor.png",
    "IsKnife": false,
    "StickerSlotsAmount": 4,
    "RarityId": 1
  },
  {
    "name": "AUG | Colony",
    "min_wear": 0.06,
    "max_wear": 0.8,
    "trade_up": true,
    "weapon_id": 8,
    "gen_id": 47,
    "collection": "The Mirage Collection",
    "rarity": "Consumer",
    "Image": "/assets/img/items/weapons/themiragecollection/aug-colony.png",
    "IsKnife": false,
    "StickerSlotsAmount": 4,
    "RarityId": 1
  },
  {
    "name": "G3SG1 | Safari Mesh",
    "min_wear": 0.06,
    "max_wear": 0.8,
    "trade_up": true,
    "weapon_id": 11,
    "gen_id": 72,
    "collection": "The Mirage Collection",
    "rarity": "Consumer",
    "Image": "/assets/img/items/weapons/themiragecollection/g3sg1-safarimesh.png",
    "IsKnife": false,
    "StickerSlotsAmount": 5,
    "RarityId": 1
  },
  {
    "name": "P250 | Bone Mask",
    "min_wear": 0.06,
    "max_wear": 0.8,
    "trade_up": true,
    "weapon_id": 36,
    "gen_id": 27,
    "collection": "The Mirage Collection",
    "rarity": "Consumer",
    "Image": "/assets/img/items/weapons/themiragecollection/p250-bonemask.png",
    "IsKnife": false,
    "StickerSlotsAmount": 4,
    "RarityId": 1
  },
  {
    "name": "P90 | Scorched",
    "min_wear": 0.06,
    "max_wear": 0.8,
    "trade_up": true,
    "weapon_id": 19,
    "gen_id": 175,
    "collection": "The Mirage Collection",
    "rarity": "Consumer",
    "Image": "/assets/img/items/weapons/themiragecollection/p90-scorched.png",
    "IsKnife": false,
    "StickerSlotsAmount": 4,
    "RarityId": 1
  },
  {
    "name": "Galil AR | Hunting Blind",
    "min_wear": 0,
    "max_wear": 0.6,
    "trade_up": true,
    "weapon_id": 13,
    "gen_id": 241,
    "collection": "The Mirage Collection",
    "rarity": "Consumer",
    "Image": "/assets/img/items/weapons/themiragecollection/galilar-huntingblind.png",
    "IsKnife": false,
    "StickerSlotsAmount": 4,
    "RarityId": 1
  }
]