[
  {
    "Name": "MP5-SD | Bamboo Garden",
    "MinWear": 0,
    "MaxWear": 0.55,
    "WeaponId": 23,
    "PaintKitId": 872,
    "Collection": "The St. Marc Collection",
    "Rarity": 1,
    "Image": "/assets/img/items/weapons/set_stmarc/weapon_mp5sd_hy_bamboo_stmarc_light_png.png"
  },
  {
    "Name": "MAC-10 | Surfwood",
    "MinWear": 0,
    "MaxWear": 0.5,
    "WeaponId": 17,
    "PaintKitId": 871,
    "Collection": "The St. Marc Collection",
    "Rarity": 1,
    "Image": "/assets/img/items/weapons/set_stmarc/weapon_mac10_sp_twigs_beach_light_png.png"
  },
  {
    "Name": "PP-Bizon | Seabird",
    "MinWear": 0,
    "MaxWear": 0.5,
    "WeaponId": 26,
    "PaintKitId": 873,
    "Collection": "The St. Marc Collection",
    "Rarity": 1,
    "Image": "/assets/img/items/weapons/set_stmarc/weapon_bizon_so_aqua_stmarc_light_png.png"
  },
  {
    "Name": "Sawed-Off | Jungle Thicket",
    "MinWear": 0,
    "MaxWear": 0.5,
    "WeaponId": 29,
    "PaintKitId": 870,
    "Collection": "The St. Marc Collection",
    "Rarity": 1,
    "Image": "/assets/img/items/weapons/set_stmarc/weapon_sawedoff_sp_palm_green_light_png.png"
  },
  {
    "Name": "Five-SeveN | Jungle",
    "MinWear": 0,
    "MaxWear": 0,
    "WeaponId": 3,
    "PaintKitId": 151,
    "Collection": "The St. Marc Collection",
    "Rarity": 1,
    "Image": "/assets/img/items/weapons/set_stmarc/weapon_fiveseven_so_jungle_light_png.png"
  },
  {
    "Name": "P90 | Sunset Lily",
    "MinWear": 0,
    "MaxWear": 0.5,
    "WeaponId": 19,
    "PaintKitId": 726,
    "Collection": "The St. Marc Collection",
    "Rarity": 2,
    "Image": "/assets/img/items/weapons/set_stmarc/weapon_p90_sp_bloom_orange_light_png.png"
  },
  {
    "Name": "M4A4 | Dark Blossom",
    "MinWear": 0,
    "MaxWear": 0.5,
    "WeaponId": 16,
    "PaintKitId": 730,
    "Collection": "The St. Marc Collection",
    "Rarity": 2,
    "Image": "/assets/img/items/weapons/set_stmarc/weapon_m4a1_sp_bud_blue_light_png.png"
  },
  {
    "Name": "XM1014 | Banana Leaf",
    "MinWear": 0,
    "MaxWear": 0.6,
    "WeaponId": 25,
    "PaintKitId": 731,
    "Collection": "The St. Marc Collection",
    "Rarity": 2,
    "Image": "/assets/img/items/weapons/set_stmarc/weapon_xm1014_hy_leaf_green_light_png.png"
  },
  {
    "Name": "Tec-9 | Rust Leaf",
    "MinWear": 0,
    "MaxWear": 0.5,
    "WeaponId": 30,
    "PaintKitId": 733,
    "Collection": "The St. Marc Collection",
    "Rarity": 2,
    "Image": "/assets/img/items/weapons/set_stmarc/weapon_tec9_sp_leaf_orange_light_png.png"
  },
  {
    "Name": "UMP-45 | Day Lily",
    "MinWear": 0,
    "MaxWear": 0.55,
    "WeaponId": 24,
    "PaintKitId": 725,
    "Collection": "The St. Marc Collection",
    "Rarity": 3,
    "Image": "/assets/img/items/weapons/set_stmarc/weapon_ump45_hy_bloom_red_light_png.png"
  },
  {
    "Name": "Five-SeveN | Crimson Blossom",
    "MinWear": 0,
    "MaxWear": 0.5,
    "WeaponId": 3,
    "PaintKitId": 729,
    "Collection": "The St. Marc Collection",
    "Rarity": 3,
    "Image": "/assets/img/items/weapons/set_stmarc/weapon_fiveseven_hy_bud_red_light_png.png"
  },
  {
    "Name": "MP7 | Teal Blossom",
    "MinWear": 0,
    "MaxWear": 0.5,
    "WeaponId": 33,
    "PaintKitId": 728,
    "Collection": "The St. Marc Collection",
    "Rarity": 3,
    "Image": "/assets/img/items/weapons/set_stmarc/weapon_mp7_sp_bud_green_light_png.png"
  },
  {
    "Name": "FAMAS | Sundown",
    "MinWear": 0,
    "MaxWear": 0.6,
    "WeaponId": 10,
    "PaintKitId": 869,
    "Collection": "The St. Marc Collection",
    "Rarity": 3,
    "Image": "/assets/img/items/weapons/set_stmarc/weapon_famas_sp_palm_sunset_light_png.png"
  },
  {
    "Name": "SSG 08 | Sea Calico",
    "MinWear": 0,
    "MaxWear": 0.5,
    "WeaponId": 40,
    "PaintKitId": 868,
    "Collection": "The St. Marc Collection",
    "Rarity": 4,
    "Image": "/assets/img/items/weapons/set_stmarc/weapon_ssg08_hy_flowers_stmarc_light_png.png"
  },
  {
    "Name": "Glock-18 | Synth Leaf",
    "MinWear": 0,
    "MaxWear": 0.7,
    "WeaponId": 4,
    "PaintKitId": 732,
    "Collection": "The St. Marc Collection",
    "Rarity": 4,
    "Image": "/assets/img/items/weapons/set_stmarc/weapon_glock_hy_leaf_blue_light_png.png"
  },
  {
    "Name": "AUG | Midnight Lily",
    "MinWear": 0,
    "MaxWear": 0.5,
    "WeaponId": 8,
    "PaintKitId": 727,
    "Collection": "The St. Marc Collection",
    "Rarity": 4,
    "Image": "/assets/img/items/weapons/set_stmarc/weapon_aug_am_bloom_blue_light_png.png"
  },
  {
    "Name": "MP9 | Wild Lily",
    "MinWear": 0,
    "MaxWear": 0.7,
    "WeaponId": 34,
    "PaintKitId": 734,
    "Collection": "The St. Marc Collection",
    "Rarity": 5,
    "Image": "/assets/img/items/weapons/set_stmarc/weapon_mp9_cu_mp9_island_floral_light_png.png"
  },
  {
    "Name": "AK-47 | Wild Lotus",
    "MinWear": 0,
    "MaxWear": 1,
    "WeaponId": 7,
    "PaintKitId": 724,
    "Collection": "The St. Marc Collection",
    "Rarity": 6,
    "Image": "/assets/img/items/weapons/set_stmarc/weapon_ak47_cu_ak_island_floral_light_png.png"
  }
]