[
  {
    "Name": "Backstab",
    "StickerId": 101,
    "Rarity": 0,
    "Image": "/assets/img/items/stickers/community01/backstab_png.png",
    "Collection": "community01",
    "SkinportSearchId": null
  },
  {
    "Name": "King on the Field",
    "StickerId": 102,
    "Rarity": 0,
    "Image": "/assets/img/items/stickers/community01/black_king_png.png",
    "Collection": "community01",
    "SkinportSearchId": null
  },
  {
    "Name": "Howling Dawn",
    "StickerId": 103,
    "Rarity": 6,
    "Image": "/assets/img/items/stickers/community01/howling_dawn_png.png",
    "Collection": "community01",
    "SkinportSearchId": null
  },
  {
    "Name": "Bomb Doge",
    "StickerId": 104,
    "Rarity": 0,
    "Image": "/assets/img/items/stickers/community01/bomb_doge_png.png",
    "Collection": "community01",
    "SkinportSearchId": null
  },
  {
    "Name": "Burn Them All",
    "StickerId": 105,
    "Rarity": 0,
    "Image": "/assets/img/items/stickers/community01/burn_them_all_png.png",
    "Collection": "community01",
    "SkinportSearchId": null
  },
  {
    "Name": "Harp of War (Holo)",
    "StickerId": 106,
    "Rarity": 1,
    "Image": "/assets/img/items/stickers/community01/harp_of_war_png.png",
    "Collection": "community01",
    "SkinportSearchId": null
  },
  {
    "Name": "Flammable (Foil)",
    "StickerId": 107,
    "Rarity": 2,
    "Image": "/assets/img/items/stickers/community01/flammable_foil_png.png",
    "Collection": "community01",
    "SkinportSearchId": null
  },
  {
    "Name": "Headhunter (Foil)",
    "StickerId": 108,
    "Rarity": 2,
    "Image": "/assets/img/items/stickers/community01/headhunter_foil_png.png",
    "Collection": "community01",
    "SkinportSearchId": null
  },
  {
    "Name": "Llama Cannon",
    "StickerId": 109,
    "Rarity": 0,
    "Image": "/assets/img/items/stickers/community01/llama_cannon_png.png",
    "Collection": "community01",
    "SkinportSearchId": null
  },
  {
    "Name": "New Sheriff (Foil)",
    "StickerId": 110,
    "Rarity": 2,
    "Image": "/assets/img/items/stickers/community01/new_sheriff_foil_png.png",
    "Collection": "community01",
    "SkinportSearchId": null
  },
  {
    "Name": "My Other Awp",
    "StickerId": 111,
    "Rarity": 0,
    "Image": "/assets/img/items/stickers/community01/other_awp_png.png",
    "Collection": "community01",
    "SkinportSearchId": null
  },
  {
    "Name": "Shave Master",
    "StickerId": 112,
    "Rarity": 0,
    "Image": "/assets/img/items/stickers/community01/shavemaster_png.png",
    "Collection": "community01",
    "SkinportSearchId": null
  },
  {
    "Name": "Rising Skull",
    "StickerId": 113,
    "Rarity": 0,
    "Image": "/assets/img/items/stickers/community01/skull_png.png",
    "Collection": "community01",
    "SkinportSearchId": null
  },
  {
    "Name": "Sneaky Beaky Like",
    "StickerId": 114,
    "Rarity": 0,
    "Image": "/assets/img/items/stickers/community01/sneaky_beaky_png.png",
    "Collection": "community01",
    "SkinportSearchId": null
  },
  {
    "Name": "Swag (Foil)",
    "StickerId": 115,
    "Rarity": 2,
    "Image": "/assets/img/items/stickers/community01/swag_foil_png.png",
    "Collection": "community01",
    "SkinportSearchId": null
  },
  {
    "Name": "Teamwork (Holo)",
    "StickerId": 116,
    "Rarity": 1,
    "Image": "/assets/img/items/stickers/community01/teamwork_holo_png.png",
    "Collection": "community01",
    "SkinportSearchId": null
  },
  {
    "Name": "To B or not to B",
    "StickerId": 117,
    "Rarity": 0,
    "Image": "/assets/img/items/stickers/community01/to_b_or_not_to_b_png.png",
    "Collection": "community01",
    "SkinportSearchId": null
  },
  {
    "Name": "Winged Defuser",
    "StickerId": 118,
    "Rarity": 0,
    "Image": "/assets/img/items/stickers/community01/winged_defuser_png.png",
    "Collection": "community01",
    "SkinportSearchId": null
  },
  {
    "Name": "Pocket BBQ",
    "StickerId": 119,
    "Rarity": 0,
    "Image": "/assets/img/items/stickers/community01/pocket_bbq_png.png",
    "Collection": "community01",
    "SkinportSearchId": null
  },
  {
    "Name": "Death Comes",
    "StickerId": 120,
    "Rarity": 0,
    "Image": "/assets/img/items/stickers/community01/death_comes_png.png",
    "Collection": "community01",
    "SkinportSearchId": null
  },
  {
    "Name": "Rekt (Holo)",
    "StickerId": 121,
    "Rarity": 1,
    "Image": "/assets/img/items/stickers/community01/rekt_png.png",
    "Collection": "community01",
    "SkinportSearchId": null
  }
]